data_profile_classifier/__init__.py
data_profile_classifier/inference.py
data_profile_classifier/preprocess.py
data_profile_classifier/train.py
data_profile_classifier/transformers.py
data_profile_classifier-0.0.3.dist-info/LICENSE.txt
data_profile_classifier-0.0.3.dist-info/METADATA
data_profile_classifier-0.0.3.dist-info/WHEEL
data_profile_classifier-0.0.3.dist-info/top_level.txt
data_profile_classifier-0.0.3.dist-info/RECORD
